pathways/__init__.py
pathways/data_validation.py
pathways/edges_matrix.py
pathways/filesystem_constants.py
pathways/lca.py
pathways/lcia.py
pathways/logging_steup.py
pathways/pathways.py
pathways/stats.py
pathways/subshares.py
pathways/utils.py
pathways/data/categories.yaml
pathways/data/classifications.csv
pathways/data/final_energy_mapping.xlsx
pathways/data/lcia_ei310.json
pathways/data/lcia_ei311.json
pathways/data/smart_categories.yaml
pathways/data/technologies_shares.yaml
pathways/data/units_conversion.yaml
pathways-1.0.2.dist-info/licenses/LICENSE
pathways-1.0.2.dist-info/METADATA
pathways-1.0.2.dist-info/WHEEL
pathways-1.0.2.dist-info/top_level.txt
pathways-1.0.2.dist-info/RECORD
