Metadata-Version: 2.4
Name: pathways
Version: 1.0.2
Summary: Scenario-level LCA of energy systems and transition pathways
Author-email: Romain Sacchi <romain.sacchi@psi.ch>
License: BSD 3-Clause License
Project-URL: Homepage, https://github.com/polca/pathways
Classifier: Intended Audience :: End Users/Desktop
Classifier: Intended Audience :: Developers
Classifier: Intended Audience :: Science/Research
Classifier: License :: OSI Approved :: BSD License
Classifier: Operating System :: MacOS :: MacOS X
Classifier: Operating System :: Microsoft :: Windows
Classifier: Operating System :: POSIX
Classifier: Programming Language :: Python
Classifier: Programming Language :: Python :: 3
Classifier: Programming Language :: Python :: 3.9
Classifier: Topic :: Scientific/Engineering :: Information Analysis
Classifier: Topic :: Scientific/Engineering :: Mathematics
Classifier: Topic :: Scientific/Engineering :: Visualization
Requires-Python: <3.13,>=3.10
License-File: LICENSE
Requires-Dist: numpy<2.0.0
Requires-Dist: pathlib
Requires-Dist: pandas
Requires-Dist: xarray
Requires-Dist: bw2calc
Requires-Dist: bw2data
Requires-Dist: scipy
Requires-Dist: premise
Requires-Dist: pyyaml
Requires-Dist: bw_processing
Requires-Dist: datapackage
Requires-Dist: pyprind
Requires-Dist: platformdirs
Requires-Dist: fs
Requires-Dist: statsmodels
Requires-Dist: SALib
Requires-Dist: pyarrow
Requires-Dist: fastparquet
Requires-Dist: edges
Dynamic: license-file
